{
  "id": "47a85a20-734c-4959-9f88-6305642f81dc",
  "prevId": "f92f587f-eff8-49c7-9216-aa57a5ecbeb9",
  "version": "7",
  "dialect": "postgresql",
  "tables": {
    "public.areas": {
      "name": "areas",
      "schema": "",
      "columns": {
        "id": {
          "name": "id",
          "type": "uuid",
          "primaryKey": true,
          "notNull": true,
          "default": "gen_random_uuid()"
        },
        "name": {
          "name": "name",
          "type": "text",
          "primaryKey": false,
          "notNull": true
        },
        "created_at": {
          "name": "created_at",
          "type": "timestamp with time zone",
          "primaryKey": false,
          "notNull": true,
          "default": "now()"
        },
        "updated_at": {
          "name": "updated_at",
          "type": "timestamp with time zone",
          "primaryKey": false,
          "notNull": true,
          "default": "now()"
        }
      },
      "indexes": {},
      "foreignKeys": {},
      "compositePrimaryKeys": {},
      "uniqueConstraints": {},
      "policies": {},
      "checkConstraints": {},
      "isRLSEnabled": false
    },
    "public.employee_tags": {
      "name": "employee_tags",
      "schema": "",
      "columns": {
        "employee_id": {
          "name": "employee_id",
          "type": "uuid",
          "primaryKey": false,
          "notNull": true
        },
        "tag_id": {
          "name": "tag_id",
          "type": "uuid",
          "primaryKey": false,
          "notNull": true
        }
      },
      "indexes": {
        "employee_tags_employee_id_tag_id_unique": {
          "name": "employee_tags_employee_id_tag_id_unique",
          "columns": [
            {
              "expression": "employee_id",
              "isExpression": false,
              "asc": true,
              "nulls": "last"
            },
            {
              "expression": "tag_id",
              "isExpression": false,
              "asc": true,
              "nulls": "last"
            }
          ],
          "isUnique": true,
          "concurrently": false,
          "method": "btree",
          "with": {}
        }
      },
      "foreignKeys": {
        "employee_tags_employee_id_employees_id_fk": {
          "name": "employee_tags_employee_id_employees_id_fk",
          "tableFrom": "employee_tags",
          "tableTo": "employees",
          "columnsFrom": [
            "employee_id"
          ],
          "columnsTo": [
            "id"
          ],
          "onDelete": "cascade",
          "onUpdate": "no action"
        },
        "employee_tags_tag_id_tags_id_fk": {
          "name": "employee_tags_tag_id_tags_id_fk",
          "tableFrom": "employee_tags",
          "tableTo": "tags",
          "columnsFrom": [
            "tag_id"
          ],
          "columnsTo": [
            "id"
          ],
          "onDelete": "cascade",
          "onUpdate": "no action"
        }
      },
      "compositePrimaryKeys": {},
      "uniqueConstraints": {},
      "policies": {},
      "checkConstraints": {},
      "isRLSEnabled": false
    },
    "public.employees": {
      "name": "employees",
      "schema": "",
      "columns": {
        "id": {
          "name": "id",
          "type": "uuid",
          "primaryKey": true,
          "notNull": true,
          "default": "gen_random_uuid()"
        },
        "code": {
          "name": "code",
          "type": "text",
          "primaryKey": false,
          "notNull": true
        },
        "last_name": {
          "name": "last_name",
          "type": "text",
          "primaryKey": false,
          "notNull": true
        },
        "first_name": {
          "name": "first_name",
          "type": "text",
          "primaryKey": false,
          "notNull": true
        },
        "avatar_color": {
          "name": "avatar_color",
          "type": "text",
          "primaryKey": false,
          "notNull": true
        },
        "is_active": {
          "name": "is_active",
          "type": "boolean",
          "primaryKey": false,
          "notNull": true,
          "default": true
        },
        "created_at": {
          "name": "created_at",
          "type": "timestamp with time zone",
          "primaryKey": false,
          "notNull": true,
          "default": "now()"
        },
        "updated_at": {
          "name": "updated_at",
          "type": "timestamp with time zone",
          "primaryKey": false,
          "notNull": true,
          "default": "now()"
        }
      },
      "indexes": {
        "employees_code_unique": {
          "name": "employees_code_unique",
          "columns": [
            {
              "expression": "code",
              "isExpression": false,
              "asc": true,
              "nulls": "last"
            }
          ],
          "isUnique": true,
          "concurrently": false,
          "method": "btree",
          "with": {}
        }
      },
      "foreignKeys": {},
      "compositePrimaryKeys": {},
      "uniqueConstraints": {},
      "policies": {},
      "checkConstraints": {},
      "isRLSEnabled": false
    },
    "public.layout_spec_versions": {
      "name": "layout_spec_versions",
      "schema": "",
      "columns": {
        "id": {
          "name": "id",
          "type": "uuid",
          "primaryKey": true,
          "notNull": true,
          "default": "gen_random_uuid()"
        },
        "area_id": {
          "name": "area_id",
          "type": "uuid",
          "primaryKey": false,
          "notNull": true
        },
        "version": {
          "name": "version",
          "type": "integer",
          "primaryKey": false,
          "notNull": true,
          "default": 1
        },
        "status": {
          "name": "status",
          "type": "text",
          "primaryKey": false,
          "notNull": true,
          "default": "'draft'"
        },
        "plan_image_url": {
          "name": "plan_image_url",
          "type": "text",
          "primaryKey": false,
          "notNull": false
        },
        "plan_image_name": {
          "name": "plan_image_name",
          "type": "text",
          "primaryKey": false,
          "notNull": false
        },
        "plan_aspect_ratio": {
          "name": "plan_aspect_ratio",
          "type": "real",
          "primaryKey": false,
          "notNull": false
        },
        "plan_image_scale": {
          "name": "plan_image_scale",
          "type": "real",
          "primaryKey": false,
          "notNull": true,
          "default": 1
        },
        "plan_image_offset_x": {
          "name": "plan_image_offset_x",
          "type": "real",
          "primaryKey": false,
          "notNull": true,
          "default": 0
        },
        "plan_image_offset_y": {
          "name": "plan_image_offset_y",
          "type": "real",
          "primaryKey": false,
          "notNull": true,
          "default": 0
        },
        "published_at": {
          "name": "published_at",
          "type": "timestamp with time zone",
          "primaryKey": false,
          "notNull": false
        },
        "created_at": {
          "name": "created_at",
          "type": "timestamp with time zone",
          "primaryKey": false,
          "notNull": true,
          "default": "now()"
        },
        "updated_at": {
          "name": "updated_at",
          "type": "timestamp with time zone",
          "primaryKey": false,
          "notNull": true,
          "default": "now()"
        }
      },
      "indexes": {
        "layout_spec_versions_area_id_version_unique": {
          "name": "layout_spec_versions_area_id_version_unique",
          "columns": [
            {
              "expression": "area_id",
              "isExpression": false,
              "asc": true,
              "nulls": "last"
            },
            {
              "expression": "version",
              "isExpression": false,
              "asc": true,
              "nulls": "last"
            }
          ],
          "isUnique": true,
          "concurrently": false,
          "method": "btree",
          "with": {}
        }
      },
      "foreignKeys": {
        "layout_spec_versions_area_id_areas_id_fk": {
          "name": "layout_spec_versions_area_id_areas_id_fk",
          "tableFrom": "layout_spec_versions",
          "tableTo": "areas",
          "columnsFrom": [
            "area_id"
          ],
          "columnsTo": [
            "id"
          ],
          "onDelete": "cascade",
          "onUpdate": "no action"
        }
      },
      "compositePrimaryKeys": {},
      "uniqueConstraints": {},
      "policies": {},
      "checkConstraints": {},
      "isRLSEnabled": false
    },
    "public.spots": {
      "name": "spots",
      "schema": "",
      "columns": {
        "id": {
          "name": "id",
          "type": "uuid",
          "primaryKey": true,
          "notNull": true,
          "default": "gen_random_uuid()"
        },
        "layout_spec_version_id": {
          "name": "layout_spec_version_id",
          "type": "uuid",
          "primaryKey": false,
          "notNull": true
        },
        "label": {
          "name": "label",
          "type": "text",
          "primaryKey": false,
          "notNull": true
        },
        "x": {
          "name": "x",
          "type": "real",
          "primaryKey": false,
          "notNull": true
        },
        "y": {
          "name": "y",
          "type": "real",
          "primaryKey": false,
          "notNull": true
        },
        "size": {
          "name": "size",
          "type": "integer",
          "primaryKey": false,
          "notNull": true,
          "default": 56
        },
        "order": {
          "name": "order",
          "type": "integer",
          "primaryKey": false,
          "notNull": true,
          "default": 0
        }
      },
      "indexes": {},
      "foreignKeys": {
        "spots_layout_spec_version_id_layout_spec_versions_id_fk": {
          "name": "spots_layout_spec_version_id_layout_spec_versions_id_fk",
          "tableFrom": "spots",
          "tableTo": "layout_spec_versions",
          "columnsFrom": [
            "layout_spec_version_id"
          ],
          "columnsTo": [
            "id"
          ],
          "onDelete": "cascade",
          "onUpdate": "no action"
        }
      },
      "compositePrimaryKeys": {},
      "uniqueConstraints": {},
      "policies": {},
      "checkConstraints": {},
      "isRLSEnabled": false
    },
    "public.tags": {
      "name": "tags",
      "schema": "",
      "columns": {
        "id": {
          "name": "id",
          "type": "uuid",
          "primaryKey": true,
          "notNull": true,
          "default": "gen_random_uuid()"
        },
        "name": {
          "name": "name",
          "type": "text",
          "primaryKey": false,
          "notNull": true
        },
        "created_at": {
          "name": "created_at",
          "type": "timestamp with time zone",
          "primaryKey": false,
          "notNull": true,
          "default": "now()"
        }
      },
      "indexes": {
        "tags_name_unique": {
          "name": "tags_name_unique",
          "columns": [
            {
              "expression": "name",
              "isExpression": false,
              "asc": true,
              "nulls": "last"
            }
          ],
          "isUnique": true,
          "concurrently": false,
          "method": "btree",
          "with": {}
        }
      },
      "foreignKeys": {},
      "compositePrimaryKeys": {},
      "uniqueConstraints": {},
      "policies": {},
      "checkConstraints": {},
      "isRLSEnabled": false
    }
  },
  "enums": {},
  "schemas": {},
  "sequences": {},
  "roles": {},
  "policies": {},
  "views": {},
  "_meta": {
    "columns": {},
    "schemas": {},
    "tables": {}
  }
}